Metadata-Version: 2.1
Name: linkparse
Version: 1.0.0
Summary: Link header parsing library for mementos
Home-page: https://github.com/lanl/link-parse
Author: Bhnauka Mahanama
Author-email: bhanuka@lanl.gov
License: UNKNOWN
Keywords: Memento,Link Header,Web archiving
Platform: UNKNOWN
Classifier: Programming Language :: Python :: 3
Classifier: Operating System :: OS Independent
Classifier: Topic :: Internet :: WWW/HTTP
Classifier: Topic :: Software Development
Requires-Python: >=3.7
License-File: LICENSE
